pyproject.toml
setup.py
src/textcpp/__init__.py
src/textcpp/operations.h
src/textcpp.egg-info/PKG-INFO
src/textcpp.egg-info/SOURCES.txt
src/textcpp.egg-info/dependency_links.txt
src/textcpp.egg-info/not-zip-safe
src/textcpp.egg-info/requires.txt
src/textcpp.egg-info/top_level.txt
src/textcpp/others/add.cpp
src/textcpp/others/bindings_others.cpp
src/textcpp/others/sub.cpp
src/textcpp/preprocessing/bindings_preprocessing.cpp
src/textcpp/preprocessing/extract_ngrams.cpp
src/textcpp/preprocessing/tokenizer.h
src/textcpp/text_utils/bindings_text_utils.cpp
src/textcpp/text_utils/count_words.cpp
src/textcpp/text_utils/frequency_count.cpp
src/textcpp/text_utils/word_frequency_count.cpp
test/test_count_words.py
test/test_frequency_count.py